{
    "info": {
     "url_png_icon_64x64": "https://github.com/ik46/fot/blob/main/Original%20Logo%20verylow.png",
     "url_png_logo": "https://github.com/ik46/fot/blob/main/Grayscale%20title%20low.png",
     "location": "Athens, Greece",
     "social": {
         "twitter_handle": "IkarosPool",
         "telegram_handle": "",
         "facebook_handle": "",
         "youtube_handle": "",
         "twitch_handle": "",
         "discord_handle": "",
         "github_handle": ""
     }
    },
    "my-pool-ids": {
        "0": "b61c90b354ea31f470a1d672b9e8d503c5930903a3158f9554a03ee9",
        "member_since": "2021-01-06",
        "name": "Ikaros Stake Pool"
    }
}
